{
  "total_files": 496,
  "files_with_syntax_errors": 88,
  "files_with_pydantic_issues": 4,
  "syntax_errors": [
    {
      "file": "scripts/security_check.py",
      "error": "Line 58: closing parenthesis ')' does not match opening parenthesis '{' on line 54",
      "line": 58
    },
    {
      "file": "scripts/validate_test_config.py",
      "error": "Line 85: unexpected indent",
      "line": 85
    },
    {
      "file": "scripts/setup_test_db.py",
      "error": "Line 19: unmatched ')'",
      "line": 19
    },
    {
      "file": "scripts/cost_monitor.py",
      "error": "Line 92: unmatched ')'",
      "line": 92
    },
    {
      "file": "tests/test_security.py",
      "error": "Line 17: unmatched ')'",
      "line": 17
    },
    {
      "file": "tests/test_multitenant_security.py",
      "error": "Line 36: unexpected indent",
      "line": 36
    },
    {
      "file": "tests/test_multi_tenant_validation.py",
      "error": "Line 26: unmatched ')'",
      "line": 26
    },
    {
      "file": "tests/test_infrastructure_resilience.py",
      "error": "Line 56: unexpected indent",
      "line": 56
    },
    {
      "file": "tests/test_performance.py",
      "error": "Line 65: invalid syntax",
      "line": 65
    },
    {
      "file": "tests/test_ai_safety_checks.py",
      "error": "Line 43: invalid syntax. Perhaps you forgot a comma?",
      "line": 43
    },
    {
      "file": "migrations/env.py",
      "error": "Line 22: unmatched ')'",
      "line": 22
    },
    {
      "file": "app/services/notification_service.py",
      "error": "Line 33: unmatched ')'",
      "line": 33
    },
    {
      "file": "app/services/user_management_service.py",
      "error": "Line 30: unmatched ')'",
      "line": 30
    },
    {
      "file": "app/services/plugin_version_manager.py",
      "error": "Line 21: unmatched ')'",
      "line": 21
    },
    {
      "file": "app/services/tenant_service.py",
      "error": "Line 20: unmatched ')'",
      "line": 20
    },
    {
      "file": "app/services/stripe_service.py",
      "error": "Line 20: unmatched ')'",
      "line": 20
    },
    {
      "file": "app/services/plugin_security_scanner.py",
      "error": "Line 22: unmatched ')'",
      "line": 22
    },
    {
      "file": "app/services/plugin_service.py",
      "error": "Line 16: unmatched ')'",
      "line": 16
    },
    {
      "file": "app/services/provisioning_service.py",
      "error": "Line 72: unmatched ')'",
      "line": 72
    },
    {
      "file": "app/services/billing_service.py",
      "error": "Line 17: unmatched ')'",
      "line": 17
    },
    {
      "file": "app/services/dns_service.py",
      "error": "Line 28: unmatched ')'",
      "line": 28
    },
    {
      "file": "app/services/analytics_service.py",
      "error": "Line 34: unmatched ')'",
      "line": 34
    },
    {
      "file": "app/services/plugin_geo_analytics.py",
      "error": "Line 19: unmatched ')'",
      "line": 19
    },
    {
      "file": "app/services/deployment_service.py",
      "error": "Line 18: unmatched ')'",
      "line": 18
    },
    {
      "file": "app/repositories/billing.py",
      "error": "Line 24: unmatched ')'",
      "line": 24
    },
    {
      "file": "app/repositories/monitoring_additional.py",
      "error": "Line 14: unmatched ')'",
      "line": 14
    },
    {
      "file": "app/core/observability.py",
      "error": "Line 140: unexpected indent",
      "line": 140
    },
    {
      "file": "app/core/middleware.py",
      "error": "Line 62: unmatched ')'",
      "line": 62
    },
    {
      "file": "app/core/response.py",
      "error": "Line 63: unexpected indent",
      "line": 63
    },
    {
      "file": "app/core/cache.py",
      "error": "Line 63: unexpected indent",
      "line": 63
    },
    {
      "file": "app/core/deps.py",
      "error": "Line 22: unmatched ')'",
      "line": 22
    },
    {
      "file": "app/core/monitoring.py",
      "error": "Line 75: unexpected indent",
      "line": 75
    },
    {
      "file": "app/core/auth.py",
      "error": "Line 23: unmatched ')'",
      "line": 23
    },
    {
      "file": "app/core/logging.py",
      "error": "Line 168: unmatched ')'",
      "line": 168
    },
    {
      "file": "app/core/sanitization.py",
      "error": "Line 86: unexpected indent",
      "line": 86
    },
    {
      "file": "app/workers/tasks/notification_tasks.py",
      "error": "Line 37: unexpected indent",
      "line": 37
    },
    {
      "file": "app/workers/tasks/deployment_tasks.py",
      "error": "Line 42: unexpected indent",
      "line": 42
    },
    {
      "file": "app/workers/tasks/monitoring_tasks.py",
      "error": "Line 85: unmatched ')'",
      "line": 85
    },
    {
      "file": "app/plugins/notifications/slack_plugin.py",
      "error": "Line 22: unexpected indent",
      "line": 22
    },
    {
      "file": "app/plugins/deployment/ssh_plugin.py",
      "error": "Line 31: unexpected indent",
      "line": 31
    },
    {
      "file": "app/plugins/deployment/aws_plugin.py",
      "error": "Line 24: unexpected indent",
      "line": 24
    },
    {
      "file": "app/plugins/monitoring/prometheus_plugin.py",
      "error": "Line 22: unexpected indent",
      "line": 22
    },
    {
      "file": "app/api/v1/billing.py",
      "error": "Line 21: unmatched ')'",
      "line": 21
    },
    {
      "file": "app/api/v1/docs.py",
      "error": "Line 28: unmatched ')'",
      "line": 28
    },
    {
      "file": "app/api/v1/tenant.py",
      "error": "Line 24: unmatched ')'",
      "line": 24
    },
    {
      "file": "app/api/v1/plugin.py",
      "error": "Line 21: unmatched ')'",
      "line": 21
    },
    {
      "file": "app/api/v1/admin.py",
      "error": "Line 30: unmatched ')'",
      "line": 30
    },
    {
      "file": "app/api/v1/deployment.py",
      "error": "Line 21: unmatched ')'",
      "line": 21
    },
    {
      "file": "app/api/v1/user_management.py",
      "error": "Line 34: unmatched ')'",
      "line": 34
    },
    {
      "file": "app/api/v1/portal.py",
      "error": "Line 31: unmatched ')'",
      "line": 31
    },
    {
      "file": "app/core/plugins/service_integration.py",
      "error": "Line 18: unmatched ')'",
      "line": 18
    },
    {
      "file": "tests/behavior/test_saas_tenant_workflows.py",
      "error": "Line 83: unmatched ')'",
      "line": 83
    },
    {
      "file": "tests/property/test_saas_property_tests.py",
      "error": "Line 30: unexpected indent",
      "line": 30
    },
    {
      "file": "tests/ai_first/test_tenant_isolation_invariants.py",
      "error": "Line 36: closing parenthesis ')' does not match opening parenthesis '['",
      "line": 36
    },
    {
      "file": "tests/ai_first/test_chaos_engineering_resilience.py",
      "error": "Line 46: unmatched ')'",
      "line": 46
    },
    {
      "file": "tests/ai_first/test_revenue_protection_invariants.py",
      "error": "Line 30: unexpected indent",
      "line": 30
    },
    {
      "file": "tests/ai_first/test_api_contract_validation.py",
      "error": "Line 82: unexpected indent",
      "line": 82
    },
    {
      "file": "tests/ai_first/test_customer_journey_behaviors.py",
      "error": "Line 43: unmatched ')'",
      "line": 43
    },
    {
      "file": "tests/contracts/test_saas_api_contracts.py",
      "error": "Line 578: unmatched ')'",
      "line": 578
    },
    {
      "file": "tests/revenue_protection/test_saas_billing_accuracy.py",
      "error": "Line 92: unmatched ')'",
      "line": 92
    },
    {
      "file": "migrations/versions/001_initial_schema.py",
      "error": "Line 24: unexpected indent",
      "line": 24
    },
    {
      "file": "migrations/versions/002_add_deployment_tables.py",
      "error": "Line 24: unexpected indent",
      "line": 24
    },
    {
      "file": "migrations/versions/005_add_enum_types.py",
      "error": "Line 24: unexpected indent",
      "line": 24
    },
    {
      "file": "portals/master_admin/api.py",
      "error": "Line 22: unmatched ')'",
      "line": 22
    },
    {
      "file": "portals/reseller/api.py",
      "error": "Line 32: unmatched ')'",
      "line": 32
    },
    {
      "file": "portals/tenant_admin/api.py",
      "error": "Line 34: unmatched ')'",
      "line": 34
    },
    {
      "file": "src/mgmt/api/cross_platform_events.py",
      "error": "Line 138: unexpected indent",
      "line": 138
    },
    {
      "file": "src/mgmt/api/tenant_orchestration.py",
      "error": "Line 17: unmatched ')'",
      "line": 17
    },
    {
      "file": "src/mgmt/api/plugin_licensing_external.py",
      "error": "Line 67: unmatched ')'",
      "line": 67
    },
    {
      "file": "src/mgmt/api/config_validation.py",
      "error": "Line 315: unmatched ')'",
      "line": 315
    },
    {
      "file": "src/mgmt/shared/audit_orchestrator.py",
      "error": "Line 24: unmatched ')'",
      "line": 24
    },
    {
      "file": "src/mgmt/shared/coordinated_disaster_recovery.py",
      "error": "Line 79: closing parenthesis '}' does not match opening parenthesis '('",
      "line": 79
    },
    {
      "file": "src/mgmt/sdks/core/utils.py",
      "error": "Line 22: unmatched ')'",
      "line": 22
    },
    {
      "file": "src/mgmt/sdks/core/exceptions.py",
      "error": "Line 25: unmatched ')'",
      "line": 25
    },
    {
      "file": "src/mgmt/services/billing_saas/models.py",
      "error": "Line 23: unmatched ')'",
      "line": 23
    },
    {
      "file": "src/mgmt/services/billing_saas/service.py",
      "error": "Line 24: unmatched ')'",
      "line": 24
    },
    {
      "file": "src/mgmt/services/kubernetes_orchestrator/service.py",
      "error": "Line 22: unmatched ')'",
      "line": 22
    },
    {
      "file": "src/mgmt/services/reseller_network/schemas.py",
      "error": "Line 15: unmatched ')'",
      "line": 15
    },
    {
      "file": "src/mgmt/services/reseller_network/models.py",
      "error": "Line 22: unmatched ')'",
      "line": 22
    },
    {
      "file": "src/mgmt/services/reseller_network/reseller_service.py",
      "error": "Line 26: unmatched ')'",
      "line": 26
    },
    {
      "file": "src/mgmt/services/plugin_licensing/service.py",
      "error": "Line 17: unmatched ')'",
      "line": 17
    },
    {
      "file": "src/mgmt/services/cost_management/service.py",
      "error": "Line 25: unmatched ')'",
      "line": 25
    },
    {
      "file": "src/mgmt/services/saas_monitoring/models.py",
      "error": "Line 328: invalid syntax",
      "line": 328
    },
    {
      "file": "src/mgmt/services/saas_monitoring/service.py",
      "error": "Line 19: unmatched ')'",
      "line": 19
    },
    {
      "file": "src/mgmt/services/tenant_management/service.py",
      "error": "Line 21: unmatched ')'",
      "line": 21
    },
    {
      "file": "src/mgmt/shared/auth/permissions.py",
      "error": "Line 32: unexpected indent",
      "line": 32
    },
    {
      "file": "src/mgmt/shared/database/connections.py",
      "error": "Line 23: unexpected indent",
      "line": 23
    },
    {
      "file": "src/mgmt/shared/security/secrets_manager.py",
      "error": "Line 26: unmatched ')'",
      "line": 26
    }
  ],
  "pydantic_issues": [
    {
      "file": "syntax_checker.py",
      "issues": [
        ".dict()",
        "Config:"
      ]
    },
    {
      "file": "syntax_fixer.py",
      "issues": [
        ".dict()",
        ".json()",
        "Config:"
      ]
    },
    {
      "file": "final_comprehensive_fix.py",
      "issues": [
        ".dict()",
        ".json()",
        ".parse_obj(",
        ".parse_raw(",
        "Config:"
      ]
    },
    {
      "file": "final_syntax_check.py",
      "issues": [
        ".dict()"
      ]
    }
  ],
  "clean_files": 120,
  "summary": {
    "total_files_scanned": 496,
    "clean_files": 120,
    "files_with_syntax_errors": 88,
    "files_with_pydantic_issues": 4,
    "syntax_error_rate": 17.74,
    "pydantic_issue_rate": 0.81,
    "overall_health": 24.19
  }
}